[
  {
    "question": "在流式处理中，滚动窗口（Tumbling Window）和滑动窗口（Sliding Window）的主要区别是什么？",
    "options": [
      "滚动窗口有重叠，滑动窗口没有重叠",
      "滚动窗口没有重叠，滑动窗口有重叠",
      "滚动窗口基于事件时间，滑动窗口基于处理时间",
      "滚动窗口只能用于批处理，滑动窗口只能用于流处理"
    ],
    "answer": 1,
    "explanation": "滚动窗口是不重叠的固定大小窗口，而滑动窗口是有重叠的固定大小窗口。滑动窗口通过指定滑动间隔来控制重叠程度。"
  },
  {
    "question": "水印（Watermark）在流式处理中的主要作用是什么？",
    "options": [
      "标记数据源的开始位置",
      "处理延迟到达的数据",
      "优化内存使用",
      "加密数据传输"
    ],
    "answer": 1,
    "explanation": "水印机制用于处理延迟到达的数据。水印 = 当前最大事件时间 - 允许的最大延迟时间，任何早于水印的事件被视为延迟事件。"
  },
  {
    "question": "Apache Flink 和 Spark Streaming 在处理模型上的根本区别是什么？",
    "options": [
      "Flink 使用微批处理，Spark Streaming 使用真正的流处理",
      "Flink 使用真正的流处理，Spark Streaming 使用微批处理",
      "两者都使用微批处理，但实现方式不同",
      "两者都使用真正的流处理，但API不同"
    ],
    "answer": 1,
    "explanation": "Apache Flink 使用真正的流处理模型（native streaming），而 Spark Streaming 最初使用微批处理（micro-batching）模型，后来的 Structured Streaming 提供了更接近真正流处理的能力。"
  },
  {
    "question": "在流式处理中，事件时间（Event Time）和处理时间（Processing Time）的区别是什么？",
    "options": [
      "事件时间是数据产生的时间，处理时间是系统处理数据的时间",
      "事件时间是系统处理数据的时间，处理时间是数据产生的时间",
      "事件时间用于批处理，处理时间用于流处理",
      "事件时间总是晚于处理时间"
    ],
    "answer": 0,
    "explanation": "事件时间是数据实际产生的时间戳，而处理时间是数据到达流处理系统并被处理的时间。事件时间对于处理乱序数据和保证结果一致性至关重要。"
  },
  {
    "question": "会话窗口（Session Window）的主要特点是什么？",
    "options": [
      "固定大小且不重叠",
      "固定大小但有重叠",
      "基于活动间隔的动态大小",
      "只能用于用户会话跟踪"
    ],
    "answer": 2,
    "explanation": "会话窗口基于活动间隔（gap duration）来动态确定窗口大小。当事件之间的间隔超过指定的会话间隔时，就认为是一个新的会话开始。"
  },
  {
    "question": "Exactly-once 处理语义保证什么？",
    "options": [
      "每个事件至少被处理一次",
      "每个事件最多被处理一次",
      "每个事件恰好被处理一次",
      "每个事件被处理零次或一次"
    ],
    "answer": 2,
    "explanation": "Exactly-once 语义保证每个事件在整个处理管道中恰好被处理一次，即使在发生故障和重试的情况下也能保证结果的一致性。"
  },
  {
    "question": "在流式处理中，状态管理的主要挑战是什么？",
    "options": [
      "状态无法持久化",
      "状态会无限增长，需要有效的状态清理机制",
      "状态只能在内存中存储",
      "状态管理只适用于批处理"
    ],
    "answer": 1,
    "explanation": "流式处理中的状态可能会无限增长，因此需要有效的状态过期和清理机制，如基于时间的TTL（Time-To-Live）或基于窗口的自动清理。"
  },
  {
    "question": "以下哪个场景最适合使用流式处理而不是批处理？",
    "options": [
      "月度财务报表生成",
      "历史数据分析",
      "实时欺诈检测",
      "数据仓库ETL作业"
    ],
    "answer": 2,
    "explanation": "实时欺诈检测需要对数据进行实时分析和响应，这是流式处理的典型应用场景。其他选项更适合使用批处理，因为它们不需要实时性。"
  }
]