[
  {
    "question": "数据湖与数据仓库的主要区别是什么？",
    "options": [
      "数据湖使用Schema-on-Write，数据仓库使用Schema-on-Read",
      "数据湖只能存储结构化数据，数据仓库存储所有类型数据",
      "数据湖使用Schema-on-Read，数据仓库使用Schema-on-Write",
      "数据湖成本更高但性能更好"
    ],
    "answer": 2,
    "explanation": "数据湖采用Schema-on-Read模式（读取时应用模式），而数据仓库采用Schema-on-Write模式（写入前必须符合预定义模式）。这使得数据湖更灵活，可以存储任何类型的数据。"
  },
  {
    "question": "现代数据湖的三区架构包括哪些区域？",
    "options": [
      "原始区、处理区、分析区",
      "原始区、精选区、服务区",
      "摄入区、存储区、查询区",
      "冷数据区、温数据区、热数据区"
    ],
    "answer": 1,
    "explanation": "现代数据湖通常采用三区架构：原始区（Raw Zone）存储未经处理的原始数据，精选区（Curated Zone）存储经过清洗和验证的数据，服务区（Serving Zone）存储为特定用例优化的数据。"
  },
  {
    "question": "以下哪个不是现代数据湖格式？",
    "options": [
      "Delta Lake",
      "Apache Iceberg",
      "Apache Hudi",
      "Apache Kafka"
    ],
    "answer": 3,
    "explanation": "Apache Kafka是一个分布式流处理平台，不是数据湖格式。Delta Lake、Apache Iceberg和Apache Hudi都是现代数据湖格式，提供ACID事务、模式演进和时间旅行查询等功能。"
  },
  {
    "question": "数据湖的主要优势不包括以下哪项？",
    "options": [
      "支持存储任何类型的数据",
      "成本效益高",
      "严格的ACID事务保证（无需额外技术）",
      "灵活性和可扩展性"
    ],
    "answer": 2,
    "explanation": "传统的数据湖本身不提供严格的ACID事务保证，这是现代数据湖格式（如Delta Lake、Iceberg、Hudi）解决的问题。原始的数据湖只是存储层，缺乏事务支持。"
  },
  {
    "question": "什么是'数据沼泽'（Data Swamp）？",
    "options": [
      "一种特殊的数据湖类型",
      "缺乏适当治理和元数据管理的数据湖",
      "用于存储备份数据的区域",
      "数据湖中的临时存储区域"
    ],
    "answer": 1,
    "explanation": "'数据沼泽'指的是缺乏适当治理、元数据管理和数据质量控制的数据湖，导致数据变得混乱、不可用或难以理解。良好的数据湖需要强大的治理策略来避免变成数据沼泽。"
  },
  {
    "question": "在选择Delta Lake、Iceberg和Hudi时，以下哪个因素最重要？",
    "options": [
      "团队现有的技术栈和技能",
      "数据湖的存储成本",
      "数据的地理分布",
      "数据的加密要求"
    ],
    "answer": 0,
    "explanation": "选择哪种现代数据湖格式主要取决于团队现有的技术栈、技能和具体需求。Delta Lake与Spark生态深度集成，Iceberg支持多引擎，Hudi专注于增量处理。技术栈匹配度是最重要的考虑因素。"
  },
  {
    "question": "湖仓一体（Lakehouse）架构的主要目标是什么？",
    "options": [
      "完全替代传统数据仓库",
      "结合数据湖的灵活性和数据仓库的可靠性",
      "降低数据存储成本",
      "简化数据工程师的工作"
    ],
    "answer": 1,
    "explanation": "湖仓一体架构的目标是结合数据湖的灵活性（存储任何类型数据、成本效益）和数据仓库的可靠性（ACID事务、模式管理、高性能查询），提供统一的数据平台。"
  },
  {
    "question": "以下哪种场景最适合使用数据湖？",
    "options": [
      "高并发的OLTP交易系统",
      "复杂的多维分析报表",
      "机器学习模型训练和特征工程",
      "实时银行转账处理"
    ],
    "answer": 2,
    "explanation": "数据湖非常适合机器学习场景，因为它可以存储大量的原始训练数据、支持特征工程，并提供灵活的数据处理能力。而OLTP交易、复杂报表和实时转账更适合传统数据库或数据仓库。"
  }
]