{
  "questions": [
    {
      "question": "Rust 生命周期的主要目的是什么？",
      "options": [
        "在运行时管理内存分配和释放",
        "确保引用在其指向的数据有效期间内使用",
        "优化程序的执行速度",
        "减少代码的编译时间"
      ],
      "answer": 1,
      "explanation": "生命周期是编译时的概念，用于确保引用不会超出其所指向数据的生命周期，从而保证内存安全。"
    },
    {
      "question": "以下哪个函数签名正确地使用了生命周期参数？",
      "options": [
        "fn longest(x: &str, y: &str) -> &str",
        "fn longest<'a>(x: &'a str, y: &'a str) -> &'a str",
        "fn longest(x: &'a str, y: &'a str) -> &'a str",
        "fn longest<'a, 'b>(x: &'a str, y: &'b str) -> &'a str"
      ],
      "answer": 1,
      "explanation": "正确的生命周期标注需要在函数名后声明生命周期参数 <'a>，然后在参数和返回类型中使用。"
    },
    {
      "question": "Rust 的生命周期省略规则有几条？",
      "options": [
        "2条",
        "3条",
        "4条",
        "5条"
      ],
      "answer": 1,
      "explanation": "Rust 有三条生命周期省略规则，覆盖了大多数常见情况。"
    },
    {
      "question": "'static 生命周期表示什么？",
      "options": [
        "变量永远不会被销毁",
        "字符串字面量和全局静态数据的生命周期",
        "程序运行期间所有数据的生命周期",
        "堆分配内存的生命周期"
      ],
      "answer": 1,
      "explanation": "'static 生命周期适用于字符串字面量和全局静态变量，它们在整个程序运行期间都有效。"
    },
    {
      "question": "当结构体包含引用字段时，必须做什么？",
      "options": [
        "为结构体实现 Copy trait",
        "为引用字段添加生命周期标注",
        "将引用转换为所有权",
        "使用 Box<T> 包装引用"
      ],
      "answer": 1,
      "explanation": "结构体中的引用字段必须标注生命周期，以告诉编译器引用的有效期。"
    },
    {
      "question": "以下哪种情况不需要显式生命周期标注？",
      "options": [
        "函数有多个输入引用参数且返回引用",
        "方法返回对 self 字段的引用",
        "函数接受两个不同生命周期的引用并返回其中一个",
        "结构体包含多个不同生命周期的引用字段"
      ],
      "answer": 1,
      "explanation": "根据生命周期省略规则3，方法中如果返回引用且其中一个参数是 &self，则自动应用 self 的生命周期。"
    },
    {
      "question": "生命周期标注会影响程序的运行时性能吗？",
      "options": [
        "会，因为需要在运行时检查生命周期",
        "会，因为增加了内存开销",
        "不会，生命周期完全是编译时的概念",
        "取决于具体的生命周期标注方式"
      ],
      "answer": 2,
      "explanation": "生命周期标注只在编译时用于类型检查，不会产生任何运行时开销。"
    },
    {
      "question": "以下代码为什么会编译失败？\nlet r;\n{\n    let x = 5;\n    r = &x;\n}\nprintln!(\"{}\", r);",
      "options": [
        "变量 x 没有实现 Debug trait",
        "引用 r 的生命周期比 x 长，导致悬空指针",
        "缺少必要的生命周期标注",
        "println! 宏不能打印引用"
      ],
      "answer": 1,
      "explanation": "变量 x 在内部作用域结束时被销毁，但引用 r 试图在外部使用它，这会导致悬空指针错误。"
    }
  ]
}